{"frames":[{"filename":"hit","frame":{"x":0,"y":0,"w":96,"h":142},"rotated":false,"trimmed":false,"spriteSourceSize":{"x":0,"y":0,"w":96,"h":142},"sourceSize":{"w":96,"h":142}},{"filename":"over","frame":{"x":97,"y":0,"w":96,"h":142},"rotated":false,"trimmed":false,"spriteSourceSize":{"x":0,"y":0,"w":96,"h":142},"sourceSize":{"w":96,"h":142}},{"filename":"up","frame":{"x":0,"y":143,"w":96,"h":142},"rotated":false,"trimmed":false,"spriteSourceSize":{"x":0,"y":0,"w":96,"h":142},"sourceSize":{"w":96,"h":142}},{"filename":"down","frame":{"x":97,"y":143,"w":96,"h":142},"rotated":false,"trimmed":false,"spriteSourceSize":{"x":0,"y":0,"w":96,"h":142},"sourceSize":{"w":96,"h":142}}],"meta":{"app":"https://www.leshylabs.com/apps/sstool/","version":"Leshy SpriteSheet Tool v0.8.4","image":"portrait.png","size":{"w":193,"h":285},"scale":1}}